airyconf
tests
