Metadata-Version: 2.1
Name: airyconf
Version: 0.0.1.1
Summary: Lightweight configuration manager
Home-page: UNKNOWN
Author: Vladimir Starostin
Author-email: v.starostin.m@gmail.com
License: MIT
Platform: UNKNOWN
Classifier: Development Status :: 3 - Alpha
Classifier: License :: OSI Approved :: MIT License
Classifier: Programming Language :: Python :: 3
Classifier: Programming Language :: Python :: 3.6
Classifier: Programming Language :: Python :: 3.7
Classifier: Programming Language :: Python :: 3.8
Classifier: Programming Language :: Python :: 3.9
Requires-Python: >=3.6
License-File: LICENSE.txt
